MANIFEST.in
README
TODO
ez_setup.py
gpl-3.0.txt
pyspec-upload.sh
setup.cfg
setup.cfg.darwin
setup.cfg.linux2
setup.cfg.win32
setup.py
setupext.py
doc/Makefile
doc/ccd.old
doc/ccd.rst
doc/ccd_FileProcessor.rst
doc/ccd_ctrans.rst
doc/ccd_formats.rst
doc/ccd_intro.rst
doc/ccd_plotting.rst
doc/ccd_sterror.rst
doc/conf.py
doc/diffractometer.rst
doc/examples.rst
doc/extensions.rst
doc/fit.rst
doc/index.rst
doc/intro.rst
doc/redirect.html
doc/spec.rst
doc/utils.rst
doc/figures/Lohmeier1993_Fig1.pdf
doc/figures/Lohmeier1993_Fig1.png
macros/README
pyspec/__init__.py
pyspec/diffractometer.py
pyspec/extensions.py
pyspec/fit.py
pyspec/fitfuncs.py
pyspec/gda.py
pyspec/hasy.py
pyspec/ipython.py
pyspec/matplotaddons.py
pyspec/mpfit.py
pyspec/spec.py
pyspec/undulator.py
pyspec/utils.py
pyspec/x1und.pro
pyspec.egg-info/PKG-INFO
pyspec.egg-info/SOURCES.txt
pyspec.egg-info/dependency_links.txt
pyspec.egg-info/top_level.txt
pyspec/calcs/__init__.py
pyspec/calcs/crystal.py
pyspec/calcs/rod.py
pyspec/calcs/sfact.py
pyspec/calcs/spacegroup.py
pyspec/calcs/structures.py
pyspec/calcs/data/AtomicConstants.dat
pyspec/calcs/data/f0_InterTables.dat
pyspec/calcs/data/f1f2_Henke.dat
pyspec/calcs/data/read.me
pyspec/ccd/__init__.py
pyspec/ccd/files.py
pyspec/ccd/plotter.py
pyspec/ccd/specext.py
pyspec/ccd/statistics.py
pyspec/ccd/transformations.py
pyspec/ccd/transformations_removed.py.txt
scripts/ccdview
scripts/logbookprint
src/README
src/ctrans.c
src/ctrans.h
src/license-sginfo
src/pylevmar.c
src/pylevmar.h
src/sgclib.c
src/sgfind.c
src/sghkl.c
src/sginfo.c
src/sginfo.h
src/sginfomodule.c
src/sgio.c
src/sgsi.c
tests/fittest.py
tests/fittest2D.py
tests/testPrinceton.py
tests/testdata.dat
tests/testgridder.py
tests/testimage.spe
tests/testimage2.spe