Metadata-Version: 1.0
Name: pyspec
Version: 0.2-r186
Summary:  pyspec : Python routuines and packages for x-ray data analysis
Home-page: http://sourceforge.net/projects/pyspec
Author: Stuart B. Wilkins
Author-email: stuwilkins@mac.com
License: UNKNOWN
Platform: any
